README.txt
setup.py
src/treemap/__init__.py
src/treemap/coverageutils.py
src/treemap/scripts.py
src/treemap/treemap.py
src/treemap.egg-info/PKG-INFO
src/treemap.egg-info/SOURCES.txt
src/treemap.egg-info/dependency_links.txt
src/treemap.egg-info/entry_points.txt
src/treemap.egg-info/top_level.txt
