Metadata-Version: 1.0
Name: treemap
Version: 1.05
Summary: Treemap creator with interactive viewer
Home-page: http://www.machine-envy.com/blog/?p=47
Author: James Casbon
Author-email: casbon@gmail.com
License: UNKNOWN
Platform: UNKNOWN
